nirfmxwlan/__init__.py
nirfmxwlan/attributes.py
nirfmxwlan/dsssmodacc.py
nirfmxwlan/dsssmodacc_configuration.py
nirfmxwlan/dsssmodacc_results.py
nirfmxwlan/enums.py
nirfmxwlan/errors.py
nirfmxwlan/examples/nirfmxwlan_dsssmodacc_grpc.py
nirfmxwlan/examples/nirfmxwlan_ofdmmodacc.py
nirfmxwlan/examples/nirfmxwlan_ofdmmodacc_mimo.py
nirfmxwlan/examples/nirfmxwlan_ofdmmodacc_trigger_based_ppdu.py
nirfmxwlan/examples/nirfmxwlan_sem.py
nirfmxwlan/examples/nirfmxwlan_sem_mimo.py
nirfmxwlan/examples/nirfmxwlan_txp.py
nirfmxwlan/grpc_session_options.py
nirfmxwlan/internal/_custom_types.py
nirfmxwlan/internal/_grpc_stub_interpreter.py
nirfmxwlan/internal/_helper.py
nirfmxwlan/internal/_library.py
nirfmxwlan/internal/_library_interpreter.py
nirfmxwlan/internal/_library_singleton.py
nirfmxwlan/internal/nidevice_pb2.py
nirfmxwlan/internal/nidevice_pb2_grpc.py
nirfmxwlan/internal/nirfmxwlan_pb2.py
nirfmxwlan/internal/nirfmxwlan_pb2_grpc.py
nirfmxwlan/internal/nirfmxwlan_restricted_pb2.py
nirfmxwlan/internal/nirfmxwlan_restricted_pb2_grpc.py
nirfmxwlan/internal/session_pb2.py
nirfmxwlan/internal/session_pb2_grpc.py
nirfmxwlan/ofdmmodacc.py
nirfmxwlan/ofdmmodacc_configuration.py
nirfmxwlan/ofdmmodacc_results.py
nirfmxwlan/powerramp.py
nirfmxwlan/powerramp_configuration.py
nirfmxwlan/powerramp_results.py
nirfmxwlan/sem.py
nirfmxwlan/sem_configuration.py
nirfmxwlan/sem_results.py
nirfmxwlan/txp.py
nirfmxwlan/txp_configuration.py
nirfmxwlan/txp_results.py
nirfmxwlan/wlan.py
nirfmxwlan-26.0.0.dist-info/licenses/LICENSE
nirfmxwlan-26.0.0.dist-info/METADATA
nirfmxwlan-26.0.0.dist-info/WHEEL
nirfmxwlan-26.0.0.dist-info/RECORD
